alphalens/__init__.py
alphalens/_version.py
alphalens/interactive.py
alphalens/performance.py
alphalens/plotting.py
alphalens/tears.py
alphalens/utils.py
alphalens/tests/__init__.py
alphalens/tests/test_performance.py
alphalens/tests/test_tears.py
alphalens/tests/test_utils.py
alphalens_eqi-1.1.0.dist-info/METADATA
alphalens_eqi-1.1.0.dist-info/RECORD
alphalens_eqi-1.1.0.dist-info/WHEEL
alphalens_eqi-1.1.0.dist-info/top_level.txt
